[{"timestamp": "2023-11-20T21:12:42", "average_rating": 4.1, "liked_count": 2043, "not_liked_count": 422, "rating_count": 2465, "review_count": 1060, "value": 83}, {"timestamp": "2023-11-20T21:47:15", "average_rating": 4.1, "liked_count": 2045, "not_liked_count": 422, "rating_count": 2467, "review_count": 1063, "value": 83}, {"timestamp": "2023-11-20T22:17:20", "average_rating": 4.1, "liked_count": 2048, "not_liked_count": 423, "rating_count": 2471, "review_count": 1065, "value": 83}, {"timestamp": "2023-11-21T00:25:32", "average_rating": 4.1, "liked_count": 2056, "not_liked_count": 423, "rating_count": 2479, "review_count": 1069, "value": 83}, {"timestamp": "2023-11-21T01:37:45", "average_rating": 4.1, "liked_count": 2057, "not_liked_count": 423, "rating_count": 2480, "review_count": 1069, "value": 83}, {"timestamp": "2023-11-21T02:22:43", "average_rating": 4.1, "liked_count": 2059, "not_liked_count": 423, "rating_count": 2482, "review_count": 1069, "value": 83}, {"timestamp": "2023-11-21T03:17:49", "average_rating": 4.1, "liked_count": 2059, "not_liked_count": 424, "rating_count": 2483, "review_count": 1069, "value": 83}, {"timestamp": "2023-11-21T04:18:06", "average_rating": 4.1, "liked_count": 2063, "not_liked_count": 425, "rating_count": 2488, "review_count": 1071, "value": 83}, {"timestamp": "2023-11-21T05:17:16", "average_rating": 4.1, "liked_count": 2067, "not_liked_count": 426, "rating_count": 2493, "review_count": 1075, "value": 83}, {"timestamp": "2023-11-21T06:18:21", "average_rating": 4.1, "liked_count": 2070, "not_liked_count": 426, "rating_count": 2496, "review_count": 1077, "value": 83}, {"timestamp": "2023-11-21T07:17:03", "average_rating": 4.1, "liked_count": 2070, "not_liked_count": 426, "rating_count": 2496, "review_count": 1077, "value": 83}, {"timestamp": "2023-11-21T08:18:31", "average_rating": 4.1, "liked_count": 2071, "not_liked_count": 427, "rating_count": 2498, "review_count": 1077, "value": 83}, {"timestamp": "2023-11-21T09:17:31", "average_rating": 4.1, "liked_count": 2072, "not_liked_count": 427, "rating_count": 2499, "review_count": 1078, "value": 83}, {"timestamp": "2023-11-21T10:18:56", "average_rating": 4.1, "liked_count": 2074, "not_liked_count": 427, "rating_count": 2501, "review_count": 1079, "value": 83}, {"timestamp": "2023-11-21T11:16:31", "average_rating": 4.1, "liked_count": 2074, "not_liked_count": 427, "rating_count": 2501, "review_count": 1079, "value": 83}, {"timestamp": "2023-11-21T12:19:36", "average_rating": 4.1, "liked_count": 2075, "not_liked_count": 427, "rating_count": 2502, "review_count": 1079, "value": 83}, {"timestamp": "2023-11-21T13:18:22", "average_rating": 4.1, "liked_count": 2075, "not_liked_count": 427, "rating_count": 2502, "review_count": 1079, "value": 83}, {"timestamp": "2023-11-21T14:17:26", "average_rating": 4.1, "liked_count": 2076, "not_liked_count": 427, "rating_count": 2503, "review_count": 1079, "value": 83}, {"timestamp": "2023-11-21T15:17:47", "average_rating": 4.1, "liked_count": 2076, "not_liked_count": 427, "rating_count": 2503, "review_count": 1079, "value": 83}, {"timestamp": "2023-11-21T16:18:44", "average_rating": 4.1, "liked_count": 2078, "not_liked_count": 427, "rating_count": 2505, "review_count": 1079, "value": 83}, {"timestamp": "2023-11-21T17:17:44", "average_rating": 4.1, "liked_count": 2078, "not_liked_count": 427, "rating_count": 2505, "review_count": 1079, "value": 83}, {"timestamp": "2023-11-21T18:18:25", "average_rating": 4.1, "liked_count": 2078, "not_liked_count": 428, "rating_count": 2506, "review_count": 1079, "value": 83}, {"timestamp": "2023-11-21T19:16:04", "average_rating": 4.1, "liked_count": 2079, "not_liked_count": 429, "rating_count": 2508, "review_count": 1080, "value": 83}, {"timestamp": "2023-11-21T20:17:21", "average_rating": 4.1, "liked_count": 2082, "not_liked_count": 430, "rating_count": 2512, "review_count": 1082, "value": 83}, {"timestamp": "2023-11-21T21:16:57", "average_rating": 4.1, "liked_count": 2082, "not_liked_count": 430, "rating_count": 2512, "review_count": 1082, "value": 83}, {"timestamp": "2023-11-21T22:17:15", "average_rating": 4.1, "liked_count": 2087, "not_liked_count": 432, "rating_count": 2519, "review_count": 1085, "value": 83}, {"timestamp": "2023-11-21T23:17:39", "average_rating": 4.1, "liked_count": 2087, "not_liked_count": 432, "rating_count": 2519, "review_count": 1085, "value": 83}, {"timestamp": "2023-11-22T00:25:53", "average_rating": 4.1, "liked_count": 2090, "not_liked_count": 433, "rating_count": 2523, "review_count": 1086, "value": 83}, {"timestamp": "2023-11-22T01:37:22", "average_rating": 4.1, "liked_count": 2090, "not_liked_count": 434, "rating_count": 2524, "review_count": 1087, "value": 83}, {"timestamp": "2023-11-22T02:22:05", "average_rating": 4.1, "liked_count": 2098, "not_liked_count": 435, "rating_count": 2533, "review_count": 1089, "value": 83}, {"timestamp": "2023-11-22T03:17:42", "average_rating": 4.1, "liked_count": 2098, "not_liked_count": 435, "rating_count": 2533, "review_count": 1089, "value": 83}, {"timestamp": "2023-11-22T04:18:07", "average_rating": 4.1, "liked_count": 2103, "not_liked_count": 436, "rating_count": 2539, "review_count": 1092, "value": 83}, {"timestamp": "2023-11-22T05:17:20", "average_rating": 4.1, "liked_count": 2108, "not_liked_count": 437, "rating_count": 2545, "review_count": 1094, "value": 83}, {"timestamp": "2023-11-22T06:18:31", "average_rating": 4.1, "liked_count": 2109, "not_liked_count": 437, "rating_count": 2546, "review_count": 1094, "value": 83}, {"timestamp": "2023-11-22T07:17:05", "average_rating": 4.1, "liked_count": 2111, "not_liked_count": 437, "rating_count": 2548, "review_count": 1095, "value": 83}, {"timestamp": "2023-11-22T08:18:22", "average_rating": 4.1, "liked_count": 2114, "not_liked_count": 438, "rating_count": 2552, "review_count": 1095, "value": 83}, {"timestamp": "2023-11-22T09:17:26", "average_rating": 4.1, "liked_count": 2115, "not_liked_count": 438, "rating_count": 2553, "review_count": 1095, "value": 83}, {"timestamp": "2023-11-22T10:17:58", "average_rating": 4.1, "liked_count": 2115, "not_liked_count": 438, "rating_count": 2553, "review_count": 1095, "value": 83}, {"timestamp": "2023-11-22T11:16:33", "average_rating": 4.1, "liked_count": 2115, "not_liked_count": 438, "rating_count": 2553, "review_count": 1095, "value": 83}, {"timestamp": "2023-11-22T12:19:32", "average_rating": 4.1, "liked_count": 2115, "not_liked_count": 438, "rating_count": 2553, "review_count": 1095, "value": 83}, {"timestamp": "2023-11-22T13:18:32", "average_rating": 4.1, "liked_count": 2117, "not_liked_count": 438, "rating_count": 2555, "review_count": 1095, "value": 83}, {"timestamp": "2023-11-22T14:17:23", "average_rating": 4.1, "liked_count": 2118, "not_liked_count": 439, "rating_count": 2557, "review_count": 1097, "value": 83}, {"timestamp": "2023-11-22T15:17:33", "average_rating": 4.1, "liked_count": 2118, "not_liked_count": 440, "rating_count": 2558, "review_count": 1097, "value": 83}, {"timestamp": "2023-11-22T16:18:27", "average_rating": 4.1, "liked_count": 2121, "not_liked_count": 440, "rating_count": 2561, "review_count": 1097, "value": 83}, {"timestamp": "2023-11-22T17:17:10", "average_rating": 4.1, "liked_count": 2121, "not_liked_count": 440, "rating_count": 2561, "review_count": 1098, "value": 83}, {"timestamp": "2023-11-22T18:18:17", "average_rating": 4.1, "liked_count": 2121, "not_liked_count": 440, "rating_count": 2561, "review_count": 1098, "value": 83}, {"timestamp": "2023-11-22T19:15:52", "average_rating": 4.1, "liked_count": 2121, "not_liked_count": 440, "rating_count": 2561, "review_count": 1098, "value": 83}, {"timestamp": "2023-11-22T20:17:34", "average_rating": 4.1, "liked_count": 2122, "not_liked_count": 440, "rating_count": 2562, "review_count": 1098, "value": 83}, {"timestamp": "2023-11-22T21:16:32", "average_rating": 4.1, "liked_count": 2122, "not_liked_count": 440, "rating_count": 2562, "review_count": 1098, "value": 83}, {"timestamp": "2023-11-22T22:17:00", "average_rating": 4.1, "liked_count": 2126, "not_liked_count": 441, "rating_count": 2567, "review_count": 1098, "value": 83}, {"timestamp": "2023-11-22T23:17:17", "average_rating": 4.1, "liked_count": 2127, "not_liked_count": 442, "rating_count": 2569, "review_count": 1099, "value": 83}, {"timestamp": "2023-11-23T00:25:01", "average_rating": 4.1, "liked_count": 2128, "not_liked_count": 443, "rating_count": 2571, "review_count": 1100, "value": 83}, {"timestamp": "2023-11-23T01:35:15", "average_rating": 4.1, "liked_count": 2131, "not_liked_count": 443, "rating_count": 2574, "review_count": 1100, "value": 83}, {"timestamp": "2023-11-23T02:20:28", "average_rating": 4.1, "liked_count": 2135, "not_liked_count": 443, "rating_count": 2578, "review_count": 1102, "value": 83}, {"timestamp": "2023-11-23T03:17:26", "average_rating": 4.1, "liked_count": 2135, "not_liked_count": 443, "rating_count": 2578, "review_count": 1102, "value": 83}, {"timestamp": "2023-11-23T04:18:09", "average_rating": 4.1, "liked_count": 2137, "not_liked_count": 444, "rating_count": 2581, "review_count": 1103, "value": 83}, {"timestamp": "2023-11-23T05:17:17", "average_rating": 4.1, "liked_count": 2137, "not_liked_count": 444, "rating_count": 2581, "review_count": 1103, "value": 83}, {"timestamp": "2023-11-23T06:18:23", "average_rating": 4.1, "liked_count": 2138, "not_liked_count": 444, "rating_count": 2582, "review_count": 1103, "value": 83}, {"timestamp": "2023-11-23T07:17:04", "average_rating": 4.1, "liked_count": 2140, "not_liked_count": 444, "rating_count": 2584, "review_count": 1105, "value": 83}, {"timestamp": "2023-11-23T08:18:12", "average_rating": 4.1, "liked_count": 2140, "not_liked_count": 444, "rating_count": 2584, "review_count": 1105, "value": 83}, {"timestamp": "2023-11-23T09:17:21", "average_rating": 4.1, "liked_count": 2141, "not_liked_count": 444, "rating_count": 2585, "review_count": 1105, "value": 83}, {"timestamp": "2023-11-23T10:17:41", "average_rating": 4.1, "liked_count": 2141, "not_liked_count": 444, "rating_count": 2585, "review_count": 1105, "value": 83}, {"timestamp": "2023-11-23T11:16:11", "average_rating": 4.1, "liked_count": 2141, "not_liked_count": 444, "rating_count": 2585, "review_count": 1105, "value": 83}, {"timestamp": "2023-11-23T12:19:30", "average_rating": 4.1, "liked_count": 2141, "not_liked_count": 444, "rating_count": 2585, "review_count": 1105, "value": 83}, {"timestamp": "2023-11-23T13:18:12", "average_rating": 4.1, "liked_count": 2141, "not_liked_count": 444, "rating_count": 2585, "review_count": 1105, "value": 83}, {"timestamp": "2023-11-23T14:17:12", "average_rating": 4.1, "liked_count": 2143, "not_liked_count": 444, "rating_count": 2587, "review_count": 1107, "value": 83}, {"timestamp": "2023-11-23T15:17:37", "average_rating": 4.1, "liked_count": 2143, "not_liked_count": 444, "rating_count": 2587, "review_count": 1107, "value": 83}, {"timestamp": "2023-11-23T16:18:17", "average_rating": 4.1, "liked_count": 2146, "not_liked_count": 444, "rating_count": 2590, "review_count": 1108, "value": 83}, {"timestamp": "2023-11-23T17:16:54", "average_rating": 4.1, "liked_count": 2147, "not_liked_count": 445, "rating_count": 2592, "review_count": 1109, "value": 83}, {"timestamp": "2023-11-23T18:18:06", "average_rating": 4.1, "liked_count": 2147, "not_liked_count": 446, "rating_count": 2593, "review_count": 1109, "value": 83}, {"timestamp": "2023-11-23T19:15:23", "average_rating": 4.1, "liked_count": 2147, "not_liked_count": 446, "rating_count": 2593, "review_count": 1109, "value": 83}, {"timestamp": "2023-11-23T20:17:31", "average_rating": 4.1, "liked_count": 2148, "not_liked_count": 446, "rating_count": 2594, "review_count": 1110, "value": 83}, {"timestamp": "2023-11-23T21:16:14", "average_rating": 4.1, "liked_count": 2151, "not_liked_count": 446, "rating_count": 2597, "review_count": 1110, "value": 83}, {"timestamp": "2023-11-23T22:17:10", "average_rating": 4.1, "liked_count": 2152, "not_liked_count": 446, "rating_count": 2598, "review_count": 1110, "value": 83}, {"timestamp": "2023-11-23T23:17:23", "average_rating": 4.1, "liked_count": 2155, "not_liked_count": 447, "rating_count": 2602, "review_count": 1113, "value": 83}, {"timestamp": "2023-11-24T00:24:11", "average_rating": 4.1, "liked_count": 2155, "not_liked_count": 447, "rating_count": 2602, "review_count": 1114, "value": 83}, {"timestamp": "2023-11-24T01:34:22", "average_rating": 4.1, "liked_count": 2156, "not_liked_count": 447, "rating_count": 2603, "review_count": 1114, "value": 83}, {"timestamp": "2023-11-24T02:19:51", "average_rating": 4.1, "liked_count": 2156, "not_liked_count": 447, "rating_count": 2603, "review_count": 1114, "value": 83}, {"timestamp": "2023-11-24T03:17:24", "average_rating": 4.1, "liked_count": 2161, "not_liked_count": 448, "rating_count": 2609, "review_count": 1114, "value": 83}, {"timestamp": "2023-11-24T04:17:54", "average_rating": 4.1, "liked_count": 2164, "not_liked_count": 449, "rating_count": 2613, "review_count": 1115, "value": 83}, {"timestamp": "2023-11-24T05:17:12", "average_rating": 4.1, "liked_count": 2164, "not_liked_count": 449, "rating_count": 2613, "review_count": 1116, "value": 83}, {"timestamp": "2023-11-24T06:18:19", "average_rating": 4.1, "liked_count": 2165, "not_liked_count": 449, "rating_count": 2614, "review_count": 1116, "value": 83}, {"timestamp": "2023-11-24T07:16:58", "average_rating": 4.1, "liked_count": 2167, "not_liked_count": 449, "rating_count": 2616, "review_count": 1117, "value": 83}, {"timestamp": "2023-11-24T08:18:16", "average_rating": 4.1, "liked_count": 2167, "not_liked_count": 449, "rating_count": 2616, "review_count": 1117, "value": 83}, {"timestamp": "2023-11-24T09:17:21", "average_rating": 4.1, "liked_count": 2167, "not_liked_count": 449, "rating_count": 2616, "review_count": 1117, "value": 83}, {"timestamp": "2023-11-24T10:17:43", "average_rating": 4.1, "liked_count": 2168, "not_liked_count": 449, "rating_count": 2617, "review_count": 1117, "value": 83}, {"timestamp": "2023-11-24T11:16:23", "average_rating": 4.1, "liked_count": 2168, "not_liked_count": 449, "rating_count": 2617, "review_count": 1117, "value": 83}, {"timestamp": "2023-11-24T12:19:29", "average_rating": 4.1, "liked_count": 2168, "not_liked_count": 449, "rating_count": 2617, "review_count": 1117, "value": 83}, {"timestamp": "2023-11-24T13:17:59", "average_rating": 4.1, "liked_count": 2170, "not_liked_count": 449, "rating_count": 2619, "review_count": 1118, "value": 83}, {"timestamp": "2023-11-24T14:17:09", "average_rating": 4.1, "liked_count": 2170, "not_liked_count": 449, "rating_count": 2619, "review_count": 1119, "value": 83}, {"timestamp": "2023-11-24T15:17:26", "average_rating": 4.1, "liked_count": 2171, "not_liked_count": 449, "rating_count": 2620, "review_count": 1120, "value": 83}, {"timestamp": "2023-11-24T16:18:28", "average_rating": 4.1, "liked_count": 2171, "not_liked_count": 449, "rating_count": 2620, "review_count": 1120, "value": 83}, {"timestamp": "2023-11-24T17:16:49", "average_rating": 4.1, "liked_count": 2171, "not_liked_count": 450, "rating_count": 2621, "review_count": 1121, "value": 83}, {"timestamp": "2023-11-24T18:18:03", "average_rating": 4.1, "liked_count": 2173, "not_liked_count": 450, "rating_count": 2623, "review_count": 1121, "value": 83}, {"timestamp": "2023-11-24T19:15:21", "average_rating": 4.1, "liked_count": 2173, "not_liked_count": 450, "rating_count": 2623, "review_count": 1121, "value": 83}, {"timestamp": "2023-11-24T20:17:21", "average_rating": 4.1, "liked_count": 2174, "not_liked_count": 450, "rating_count": 2624, "review_count": 1122, "value": 83}, {"timestamp": "2023-11-24T21:16:06", "average_rating": 4.1, "liked_count": 2177, "not_liked_count": 450, "rating_count": 2627, "review_count": 1122, "value": 83}, {"timestamp": "2023-11-24T22:17:16", "average_rating": 4.1, "liked_count": 2180, "not_liked_count": 450, "rating_count": 2630, "review_count": 1123, "value": 83}, {"timestamp": "2023-11-24T23:17:15", "average_rating": 4.1, "liked_count": 2179, "not_liked_count": 451, "rating_count": 2630, "review_count": 1124, "value": 83}, {"timestamp": "2023-11-25T00:23:54", "average_rating": 4.1, "liked_count": 2185, "not_liked_count": 453, "rating_count": 2638, "review_count": 1126, "value": 83}, {"timestamp": "2023-11-25T01:33:30", "average_rating": 4.1, "liked_count": 2187, "not_liked_count": 453, "rating_count": 2640, "review_count": 1129, "value": 83}, {"timestamp": "2023-11-25T02:19:15", "average_rating": 4.1, "liked_count": 2190, "not_liked_count": 454, "rating_count": 2644, "review_count": 1129, "value": 83}, {"timestamp": "2023-11-25T03:17:26", "average_rating": 4.1, "liked_count": 2191, "not_liked_count": 456, "rating_count": 2647, "review_count": 1132, "value": 83}, {"timestamp": "2023-11-25T04:17:56", "average_rating": 4.1, "liked_count": 2194, "not_liked_count": 457, "rating_count": 2651, "review_count": 1132, "value": 83}, {"timestamp": "2023-11-25T05:17:02", "average_rating": 4.1, "liked_count": 2196, "not_liked_count": 458, "rating_count": 2654, "review_count": 1132, "value": 83}, {"timestamp": "2023-11-25T06:18:09", "average_rating": 4.1, "liked_count": 2196, "not_liked_count": 459, "rating_count": 2655, "review_count": 1133, "value": 83}, {"timestamp": "2023-11-25T07:16:22", "average_rating": 4.1, "liked_count": 2203, "not_liked_count": 460, "rating_count": 2663, "review_count": 1134, "value": 83}, {"timestamp": "2023-11-25T08:18:11", "average_rating": 4.1, "liked_count": 2203, "not_liked_count": 460, "rating_count": 2663, "review_count": 1136, "value": 83}, {"timestamp": "2023-11-25T09:16:35", "average_rating": 4.1, "liked_count": 2204, "not_liked_count": 460, "rating_count": 2664, "review_count": 1136, "value": 83}, {"timestamp": "2023-11-25T10:17:08", "average_rating": 4.1, "liked_count": 2205, "not_liked_count": 460, "rating_count": 2665, "review_count": 1136, "value": 83}, {"timestamp": "2023-11-25T11:15:30", "average_rating": 4.1, "liked_count": 2205, "not_liked_count": 460, "rating_count": 2665, "review_count": 1135, "value": 83}, {"timestamp": "2023-11-25T12:19:21", "average_rating": 4.1, "liked_count": 2205, "not_liked_count": 461, "rating_count": 2666, "review_count": 1136, "value": 83}, {"timestamp": "2023-11-25T13:17:29", "average_rating": 4.1, "liked_count": 2205, "not_liked_count": 461, "rating_count": 2666, "review_count": 1137, "value": 83}, {"timestamp": "2023-11-25T14:16:32", "average_rating": 4.1, "liked_count": 2207, "not_liked_count": 461, "rating_count": 2668, "review_count": 1138, "value": 83}, {"timestamp": "2023-11-25T15:17:03", "average_rating": 4.1, "liked_count": 2207, "not_liked_count": 461, "rating_count": 2668, "review_count": 1138, "value": 83}, {"timestamp": "2023-11-25T16:18:01", "average_rating": 4.1, "liked_count": 2209, "not_liked_count": 461, "rating_count": 2670, "review_count": 1140, "value": 83}, {"timestamp": "2023-11-25T17:16:28", "average_rating": 4.1, "liked_count": 2211, "not_liked_count": 462, "rating_count": 2673, "review_count": 1142, "value": 83}, {"timestamp": "2023-11-25T18:17:53", "average_rating": 4.1, "liked_count": 2211, "not_liked_count": 462, "rating_count": 2673, "review_count": 1142, "value": 83}, {"timestamp": "2023-11-25T19:14:58", "average_rating": 4.1, "liked_count": 2212, "not_liked_count": 463, "rating_count": 2675, "review_count": 1142, "value": 83}, {"timestamp": "2023-11-25T20:17:21", "average_rating": 4.1, "liked_count": 2216, "not_liked_count": 463, "rating_count": 2679, "review_count": 1146, "value": 83}, {"timestamp": "2023-11-25T21:15:57", "average_rating": 4.1, "liked_count": 2218, "not_liked_count": 463, "rating_count": 2681, "review_count": 1146, "value": 83}, {"timestamp": "2023-11-25T22:17:01", "average_rating": 4.1, "liked_count": 2219, "not_liked_count": 463, "rating_count": 2682, "review_count": 1149, "value": 83}, {"timestamp": "2023-11-25T23:17:34", "average_rating": 4.1, "liked_count": 2224, "not_liked_count": 465, "rating_count": 2689, "review_count": 1150, "value": 83}, {"timestamp": "2023-11-26T00:26:38", "average_rating": 4.1, "liked_count": 2225, "not_liked_count": 465, "rating_count": 2690, "review_count": 1151, "value": 83}, {"timestamp": "2023-11-26T01:37:49", "average_rating": 4.1, "liked_count": 2228, "not_liked_count": 465, "rating_count": 2693, "review_count": 1153, "value": 83}, {"timestamp": "2023-11-26T02:20:49", "average_rating": 4.1, "liked_count": 2229, "not_liked_count": 465, "rating_count": 2694, "review_count": 1154, "value": 83}, {"timestamp": "2023-11-26T03:17:18", "average_rating": 4.1, "liked_count": 2230, "not_liked_count": 466, "rating_count": 2696, "review_count": 1154, "value": 83}, {"timestamp": "2023-11-26T04:17:54", "average_rating": 4.1, "liked_count": 2230, "not_liked_count": 466, "rating_count": 2696, "review_count": 1154, "value": 83}, {"timestamp": "2023-11-26T05:17:05", "average_rating": 4.1, "liked_count": 2239, "not_liked_count": 469, "rating_count": 2708, "review_count": 1158, "value": 83}, {"timestamp": "2023-11-26T06:18:15", "average_rating": 4.1, "liked_count": 2241, "not_liked_count": 469, "rating_count": 2710, "review_count": 1158, "value": 83}, {"timestamp": "2023-11-26T07:16:39", "average_rating": 4.1, "liked_count": 2243, "not_liked_count": 469, "rating_count": 2712, "review_count": 1158, "value": 83}, {"timestamp": "2023-11-26T08:17:50", "average_rating": 4.1, "liked_count": 2244, "not_liked_count": 471, "rating_count": 2715, "review_count": 1161, "value": 83}, {"timestamp": "2023-11-26T09:16:44", "average_rating": 4.1, "liked_count": 2244, "not_liked_count": 471, "rating_count": 2715, "review_count": 1161, "value": 83}, {"timestamp": "2023-11-26T10:17:36", "average_rating": 4.1, "liked_count": 2245, "not_liked_count": 470, "rating_count": 2715, "review_count": 1161, "value": 83}, {"timestamp": "2023-11-26T11:15:37", "average_rating": 4.1, "liked_count": 2245, "not_liked_count": 470, "rating_count": 2715, "review_count": 1161, "value": 83}, {"timestamp": "2023-11-26T12:19:12", "average_rating": 4.1, "liked_count": 2245, "not_liked_count": 470, "rating_count": 2715, "review_count": 1161, "value": 83}, {"timestamp": "2023-11-26T13:17:33", "average_rating": 4.1, "liked_count": 2245, "not_liked_count": 470, "rating_count": 2715, "review_count": 1161, "value": 83}, {"timestamp": "2023-11-26T14:16:31", "average_rating": 4.1, "liked_count": 2245, "not_liked_count": 471, "rating_count": 2716, "review_count": 1161, "value": 83}, {"timestamp": "2023-11-26T15:17:05", "average_rating": 4.1, "liked_count": 2245, "not_liked_count": 471, "rating_count": 2716, "review_count": 1162, "value": 83}, {"timestamp": "2023-11-26T16:17:51", "average_rating": 4.1, "liked_count": 2245, "not_liked_count": 471, "rating_count": 2716, "review_count": 1162, "value": 83}, {"timestamp": "2023-11-26T17:16:29", "average_rating": 4.1, "liked_count": 2245, "not_liked_count": 471, "rating_count": 2716, "review_count": 1162, "value": 83}, {"timestamp": "2023-11-26T18:17:51", "average_rating": 4.1, "liked_count": 2247, "not_liked_count": 471, "rating_count": 2718, "review_count": 1162, "value": 83}, {"timestamp": "2023-11-26T19:15:03", "average_rating": 4.1, "liked_count": 2247, "not_liked_count": 472, "rating_count": 2719, "review_count": 1162, "value": 83}, {"timestamp": "2023-11-26T20:17:23", "average_rating": 4.1, "liked_count": 2248, "not_liked_count": 472, "rating_count": 2720, "review_count": 1163, "value": 83}, {"timestamp": "2023-11-26T21:16:23", "average_rating": 4.1, "liked_count": 2249, "not_liked_count": 472, "rating_count": 2721, "review_count": 1163, "value": 83}, {"timestamp": "2023-11-26T22:17:05", "average_rating": 4.1, "liked_count": 2252, "not_liked_count": 474, "rating_count": 2726, "review_count": 1165, "value": 83}, {"timestamp": "2023-11-26T23:17:09", "average_rating": 4.1, "liked_count": 2259, "not_liked_count": 475, "rating_count": 2734, "review_count": 1165, "value": 83}, {"timestamp": "2023-11-27T00:25:39", "average_rating": 4.1, "liked_count": 2259, "not_liked_count": 475, "rating_count": 2734, "review_count": 1165, "value": 83}, {"timestamp": "2023-11-27T01:35:45", "average_rating": 4.1, "liked_count": 2261, "not_liked_count": 476, "rating_count": 2737, "review_count": 1169, "value": 83}, {"timestamp": "2023-11-27T02:20:39", "average_rating": 4.1, "liked_count": 2264, "not_liked_count": 477, "rating_count": 2741, "review_count": 1169, "value": 83}, {"timestamp": "2023-11-27T03:17:26", "average_rating": 4.1, "liked_count": 2268, "not_liked_count": 477, "rating_count": 2745, "review_count": 1171, "value": 83}, {"timestamp": "2023-11-27T04:18:04", "average_rating": 4.1, "liked_count": 2271, "not_liked_count": 478, "rating_count": 2749, "review_count": 1172, "value": 83}, {"timestamp": "2023-11-27T05:17:12", "average_rating": 4.1, "liked_count": 2271, "not_liked_count": 477, "rating_count": 2748, "review_count": 1172, "value": 83}, {"timestamp": "2023-11-27T06:18:27", "average_rating": 4.1, "liked_count": 2273, "not_liked_count": 477, "rating_count": 2750, "review_count": 1172, "value": 83}, {"timestamp": "2023-11-27T07:17:07", "average_rating": 4.1, "liked_count": 2275, "not_liked_count": 477, "rating_count": 2752, "review_count": 1175, "value": 83}, {"timestamp": "2023-11-27T08:18:35", "average_rating": 4.1, "liked_count": 2276, "not_liked_count": 477, "rating_count": 2753, "review_count": 1175, "value": 83}, {"timestamp": "2023-11-27T09:17:49", "average_rating": 4.1, "liked_count": 2277, "not_liked_count": 477, "rating_count": 2754, "review_count": 1176, "value": 83}, {"timestamp": "2023-11-27T10:17:48", "average_rating": 4.1, "liked_count": 2277, "not_liked_count": 477, "rating_count": 2754, "review_count": 1176, "value": 83}, {"timestamp": "2023-11-27T11:16:29", "average_rating": 4.1, "liked_count": 2277, "not_liked_count": 477, "rating_count": 2754, "review_count": 1176, "value": 83}, {"timestamp": "2023-11-27T12:19:28", "average_rating": 4.1, "liked_count": 2277, "not_liked_count": 477, "rating_count": 2754, "review_count": 1176, "value": 83}, {"timestamp": "2023-11-27T13:18:13", "average_rating": 4.1, "liked_count": 2277, "not_liked_count": 477, "rating_count": 2754, "review_count": 1176, "value": 83}, {"timestamp": "2023-11-27T14:17:19", "average_rating": 4.1, "liked_count": 2277, "not_liked_count": 477, "rating_count": 2754, "review_count": 1176, "value": 83}, {"timestamp": "2023-11-27T15:17:51", "average_rating": 4.1, "liked_count": 2277, "not_liked_count": 477, "rating_count": 2754, "review_count": 1176, "value": 83}, {"timestamp": "2023-11-27T16:18:37", "average_rating": 4.1, "liked_count": 2277, "not_liked_count": 477, "rating_count": 2754, "review_count": 1176, "value": 83}, {"timestamp": "2023-11-27T17:17:12", "average_rating": 4.1, "liked_count": 2277, "not_liked_count": 477, "rating_count": 2754, "review_count": 1176, "value": 83}, {"timestamp": "2023-11-27T18:18:19", "average_rating": 4.1, "liked_count": 2277, "not_liked_count": 477, "rating_count": 2754, "review_count": 1176, "value": 83}, {"timestamp": "2023-11-27T19:15:23", "average_rating": 4.1, "liked_count": 2277, "not_liked_count": 477, "rating_count": 2754, "review_count": 1176, "value": 83}, {"timestamp": "2023-11-27T20:18:03", "average_rating": 4.1, "liked_count": 2277, "not_liked_count": 477, "rating_count": 2754, "review_count": 1176, "value": 83}, {"timestamp": "2023-11-27T21:16:51", "average_rating": 4.1, "liked_count": 2278, "not_liked_count": 477, "rating_count": 2755, "review_count": 1176, "value": 83}, {"timestamp": "2023-11-27T22:16:55", "average_rating": 4.1, "liked_count": 2278, "not_liked_count": 477, "rating_count": 2755, "review_count": 1176, "value": 83}, {"timestamp": "2023-11-27T23:17:35", "average_rating": 4.1, "liked_count": 2278, "not_liked_count": 477, "rating_count": 2755, "review_count": 1176, "value": 83}, {"timestamp": "2023-11-28T00:25:13", "average_rating": 4.1, "liked_count": 2278, "not_liked_count": 477, "rating_count": 2755, "review_count": 1176, "value": 83}, {"timestamp": "2023-11-28T01:36:05", "average_rating": 4.1, "liked_count": 2280, "not_liked_count": 477, "rating_count": 2757, "review_count": 1177, "value": 83}, {"timestamp": "2023-11-28T02:20:58", "average_rating": 4.1, "liked_count": 2281, "not_liked_count": 478, "rating_count": 2759, "review_count": 1178, "value": 83}, {"timestamp": "2023-11-28T03:17:33", "average_rating": 4.1, "liked_count": 2281, "not_liked_count": 478, "rating_count": 2759, "review_count": 1178, "value": 83}, {"timestamp": "2023-11-28T04:18:02", "average_rating": 4.1, "liked_count": 2282, "not_liked_count": 478, "rating_count": 2760, "review_count": 1178, "value": 83}, {"timestamp": "2023-11-28T05:17:18", "average_rating": 4.1, "liked_count": 2283, "not_liked_count": 479, "rating_count": 2762, "review_count": 1180, "value": 83}, {"timestamp": "2023-11-28T06:18:21", "average_rating": 4.1, "liked_count": 2283, "not_liked_count": 479, "rating_count": 2762, "review_count": 1180, "value": 83}, {"timestamp": "2023-11-28T07:17:01", "average_rating": 4.1, "liked_count": 2285, "not_liked_count": 479, "rating_count": 2764, "review_count": 1182, "value": 83}, {"timestamp": "2023-11-28T08:18:17", "average_rating": 4.1, "liked_count": 2285, "not_liked_count": 479, "rating_count": 2764, "review_count": 1182, "value": 83}, {"timestamp": "2023-11-28T09:17:23", "average_rating": 4.1, "liked_count": 2285, "not_liked_count": 479, "rating_count": 2764, "review_count": 1182, "value": 83}, {"timestamp": "2023-11-28T10:17:49", "average_rating": 4.1, "liked_count": 2286, "not_liked_count": 480, "rating_count": 2766, "review_count": 1182, "value": 83}, {"timestamp": "2023-11-28T11:16:35", "average_rating": 4.1, "liked_count": 2286, "not_liked_count": 480, "rating_count": 2766, "review_count": 1182, "value": 83}, {"timestamp": "2023-11-28T12:19:32", "average_rating": 4.1, "liked_count": 2286, "not_liked_count": 480, "rating_count": 2766, "review_count": 1183, "value": 83}, {"timestamp": "2023-11-28T13:18:11", "average_rating": 4.1, "liked_count": 2287, "not_liked_count": 480, "rating_count": 2767, "review_count": 1183, "value": 83}, {"timestamp": "2023-11-28T14:17:22", "average_rating": 4.1, "liked_count": 2287, "not_liked_count": 480, "rating_count": 2767, "review_count": 1183, "value": 83}]